streetcrawl/__init__.py
streetcrawl/__main__.py
streetcrawl/catalogue.py
streetcrawl/pano.py
streetcrawl/pano_folder.py
streetcrawl/pano_folder_glued.py
streetcrawl/pano_folder_simple.py
streetcrawl/pano_id.py
streetcrawl/panos.py
streetcrawl/points_in_square.py
streetcrawl/saver.py
streetcrawl-0.1.0.dist-info/LICENSE
streetcrawl-0.1.0.dist-info/WHEEL
streetcrawl-0.1.0.dist-info/METADATA
streetcrawl-0.1.0.dist-info/RECORD
